{
  "project": "Ananta Platform (WebRTC & Secure Exchange)",
  "version": "1.0.0-draft",
  "description": "Erweiterung von EDS Lite zu einer dezentralen WebRTC-Plattform für sichere Kommunikation und Dateiaustausch.",
  "tasks": [
    {
      "id": "SEC-001",
      "title": "AndroidKeyStore Integration",
      "description": "Verschlüsselung des privaten Schlüssels der Nutzeridentität mittels AndroidKeyStore (AES/GCM).",
      "status": "todo",
      "priority": "high",
      "assignee": "Junie"
    },
    {
      "id": "NET-004",
      "title": "WebRTC Signaling Service",
      "description": "Implementierung eines dezentralen oder einfachen Signaling-Mechanismus für Internet-Verbindungen.",
      "status": "todo",
      "priority": "medium",
      "assignee": "Junie"
    }
  ],
  "architecture_goals": [
    "Vollständige Dezentralität (kein zentraler Server außer Signaling/STUN)",
    "Ende-zu-Ende Verschlüsselung für alle Transfers",
    "Offline-First Ansatz für das Trust-Ranking"
  ]
}
